camel_model/CamelModel.py
camel_model/__init__.py
camel_model-0.1.2.dist-info/WHEEL
camel_model-0.1.2.dist-info/METADATA
camel_model-0.1.2.dist-info/RECORD
